yupiwrap/__init__.py
yupiwrap/tracktable.py
yupiwrap/traja.py
yupiwrap/utils.py
yupiwrap-0.1.2.dist-info/LICENSE
yupiwrap-0.1.2.dist-info/WHEEL
yupiwrap-0.1.2.dist-info/METADATA
yupiwrap-0.1.2.dist-info/RECORD
