Metadata-Version: 2.1
Name: yupiwrap
Version: 0.1.2
Summary: 
Author: Gustavo Viera-López
Author-email: gvieralopez@gmail.com
Requires-Python: >=3.7,<4.0
Classifier: Programming Language :: Python :: 3
Classifier: Programming Language :: Python :: 3.10
Classifier: Programming Language :: Python :: 3.7
Classifier: Programming Language :: Python :: 3.8
Classifier: Programming Language :: Python :: 3.9
Requires-Dist: tracktable (>=1.5.0,<2.0.0)
Requires-Dist: traja (>=0.2.8,<0.3.0)
Requires-Dist: yupi (>=0.8.0,<0.9.0)
